<?xml version="1.0"?>
<SegmentSet xmlns="http://tempuri.org/X12ParserSpecification.xsd"
    >
  <Name>4010</Name>
  <Segment SegmentId="ISA" >
    <Element Name="Author Information Qualifier" Required="true" Type="ID" MinLength="2" MaxLength="2">
      <Allowed ID="00">No Authorization Information Present</Allowed>
      <Allowed ID="03">Additional Data Identification</Allowed>
    </Element>
    <Element Name="Author Information" Required="true" Type="AN" MinLength="10" MaxLength="10" />
    <Element Name="Security Information Qualifer" Required="true" Type="ID" MinLength="2" MaxLength="2">
      <Allowed ID="00">No Security Information Present</Allowed>
      <Allowed ID="01">Password</Allowed>
    </Element>
    <Element Name="Security Information" Required="true" Type="AN" MinLength="10" MaxLength="2" />
    <Element Name="Interchange ID Qualifier" Required="true" Type="ID" MinLength="2" MaxLength="2">
      <Allowed ID="01">Duns (Dun &amp; Bradstreet)</Allowed>
      <Allowed ID="14">Duns Plus Suffix</Allowed>
      <Allowed ID="20">Health Insurance Number (HIN)</Allowed>
      <Allowed ID="27">Carrier Identification Number as assigned by Health Care Financing Administration (HCFA)</Allowed>
      <Allowed ID="28">Fiscal Intermediary Identification Number as assigned by Health Care Financing Administration (HCFA)</Allowed>
      <Allowed ID="29">Medicare Provider and Supplier Identification Number as assigned by Health Care Financing Administration (HCFA)</Allowed>
      <Allowed ID="30">U.S. Federal Tax Identification Number</Allowed>
      <Allowed ID="33">National Association of Insurance Commissioners Company Code (NAIC)</Allowed>
      <Allowed ID="ZZ">Mutually Defined</Allowed>
    </Element>
    <Element Name="Interchange Sender ID" Required="true" Type="AN" MinLength="15" MaxLength="15" />
    <Element Name="Interchange ID Qualifier" Required="true" Type="ID" MinLength="2" MaxLength="2">
      <Allowed ID="01">Duns (Dun &amp; Bradstreet)</Allowed>
      <Allowed ID="14">Duns Plus Suffix</Allowed>
      <Allowed ID="20">Health Insurance Number (HIN)</Allowed>
      <Allowed ID="27">Carrier Identification Number as assigned by Health Care Financing Administration (HCFA)</Allowed>
      <Allowed ID="28">Fiscal Intermediary Identification Number as assigned by Health Care Financing Administration (HCFA)</Allowed>
      <Allowed ID="29">Medicare Provider and Supplier Identification Number as assigned by Health Care Financing Administration (HCFA)</Allowed>
      <Allowed ID="30">U.S. Federal Tax Identification Number</Allowed>
      <Allowed ID="33">National Association of Insurance Commissioners Company Code (NAIC)</Allowed>
      <Allowed ID="ZZ">Mutually Defined</Allowed>
    </Element>
    <Element Name="Interchange Receiver ID" Required="true" Type="AN" MinLength="15" MaxLength="15" />
    <Element Name="Interchange Date" Required="true" Type="DT" MinLength="6" MaxLength="6" />
    <Element Name="Interchange Time" Required="true" Type="TM" MinLength="4" MaxLength="4" />
    <Element Name="Inter Control Standards Identifier" Required="true" Type="ID" MinLength="1" MaxLength="1">
      <Allowed ID="U">U.S. EDI Community of ASC X12, TDCC, and UCS</Allowed>
    </Element>
    <Element Name="Inter Control Version Number" Required="true" Type="ID" MinLength="5" MaxLength="5" />
    <Element Name="Inter Control Number" Required="true" Type="N" MinLength="9" MaxLength="9" />
    <Element Name="Acknowlegment Requested" Required="true" Type="ID" MinLength="1" MaxLength="1">
      <Allowed ID="0">No Acknowledgment Requested</Allowed>
      <Allowed ID="1">Interchange Acknowledgment Requested</Allowed>
    </Element>
    <Element Name="Usage Indicator" Required="true" Type="ID" MinLength="1" MaxLength="1">
      <Allowed ID="P">Production Data</Allowed>
      <Allowed ID="T">Test Data</Allowed>
    </Element>
    <Element Name="Component Element Separator" Required="true" Type="AN" MinLength="1" MaxLength="1" />
  </Segment>
  <Segment SegmentId="IEA">
    <Element Name="Number of Included Functional Groups" Required="true" Type="N" MinLength="1" MaxLength="5" />
    <Element Name="Interchange Control Number" Required="true" Type="N" MinLength="9" MaxLength="9" />
  </Segment>
  <Segment SegmentId="GS">
    <Element Name="Functional Identifier Code" Required="true" Type="ID" MinLength="2" MaxLength="2">
      <Allowed ID="BE">Benefit Enrollment and Maintenance (834)</Allowed>
    </Element>
    <Element Name="Application Sender's Code" Required="true" Type="AN" MinLength="2" MaxLength="15" />
    <Element Name="Application Receiver's Code" Required="true" Type="AN" MinLength="2" MaxLength="15" />
    <Element Name="Date" Required="true" Type="DT" MinLength="8" MaxLength="8" />
    <Element Name="Time" Required="true" Type="TM" MinLength="4" MaxLength="8" />
    <Element Name="Group Control Number" Required="true" Type="N" MinLength="1" MaxLength="9" />
    <Element Name="Responsible Agency Code" Required="true" Type="ID" MinLength="1" MaxLength="2">
      <Allowed ID="X">Accredited Standards Committee X12</Allowed>
    </Element>
    <Element Name="Version/Release/Industry Identifier Code" Required="true" Type="AN" MinLength="1" MaxLength="12">
    </Element>
  </Segment>
  <Segment SegmentId="GE">
    <Element Name="Number of Transaction Sets Included" Required="true" Type="N" MinLength="1" MaxLength="6"/>
    <Element Name="Group Control Number" Required="true" Type="N" MinLength="1" MaxLength="9" />
  </Segment>
  <Segment SegmentId="ST">
    <Element Name="Transaction Set Identifier Code" Required="true" Type="ID" MinLength="3" MaxLength="3" />
    <Element Name="Transaction Set Control Number" Required="true" Type="AN" MinLength="4" MaxLength="9" />
  </Segment>

  <Segment SegmentId="HL">
    <Element Name="Hierarchical ID Number" Required="true" Type="AN" MinLength="1" MaxLength="12" />
    <Element Name="Hierarchical Parent ID Number" Required="false" Type="AN" MinLength="1" MaxLength="12" />
  </Segment>
</SegmentSet>